{
  "_class": "group",
  "do_objectID": "E5BBD439-3FA7-4FDC-BB59-E0B1873F2DA3",
  "exportOptions": {
    "_class": "exportOptions",
    "exportFormats": [
    ],
    "includedLayerIds": [
    ],
    "layerOptions": 0,
    "shouldTrim": false
  },
  "frame": {
    "_class": "rect",
    "constrainProportions": false,
    "height": 555,
    "width": 1024,
    "x": 0,
    "y": 1040
  },
  "hasClickThrough": false,
  "isFlippedHorizontal": false,
  "isFlippedVertical": false,
  "isLocked": false,
  "isVisible": true,
  "layerListExpandedType": 0,
  "layers": [
    {
      "class": "shapeGroup",
      "id": "C0E42096-88E4-4DB7-AD8D-6478EE18D297"
    },
    {
      "class": "text",
      "id": "31FCE51E-1BD1-4A42-B21A-87A777178D1E"
    },
    {
      "class": "text",
      "id": "CD24EB8C-69C3-4597-ACAE-986CE0E86BFC"
    },
    {
      "class": "shapeGroup",
      "id": "5FFE41CC-F157-4DC1-BAFE-D2E5788FFF91"
    },
    {
      "class": "shapeGroup",
      "id": "D715DB2E-D01F-4A05-80EB-6C012B34EFC8"
    },
    {
      "class": "shapeGroup",
      "id": "9B5EF22D-7E87-447F-83C1-C8744EB0B99F"
    }
  ],
  "name": "Group",
  "nameIsFixed": false,
  "resizingConstraint": 63,
  "resizingType": 0,
  "rotation": 0,
  "shouldBreakMaskChain": false,
  "style": {
    "_class": "style",
    "endDecorationType": 0,
    "miterLimit": 10,
    "startDecorationType": 0
  }
}